antescofo/__init__.py
antescofo/client.py
antescofo/constants.py
antescofo/events.py
antescofo/exceptions.py
antescofo/osc.py
antescofo/score.py
antescofo/types.py
antescofo-0.1.1.dist-info/licenses/LICENSE
antescofo-0.1.1.dist-info/METADATA
antescofo-0.1.1.dist-info/WHEEL
antescofo-0.1.1.dist-info/top_level.txt
antescofo-0.1.1.dist-info/RECORD
