Metadata-Version: 2.4
Name: antescofo
Version: 0.1.1
Summary: A Python interface for Antescofo, the score following and synchronous programming language for music
Author: Antescofo Python Interface Contributors
License: MIT
Project-URL: Homepage, https://github.com/yourusername/antescofo
Project-URL: Documentation, https://antescofo-doc.ircam.fr/
Project-URL: Repository, https://github.com/yourusername/antescofo
Project-URL: Bug Tracker, https://github.com/yourusername/antescofo/issues
Keywords: antescofo,music,osc,score-following,real-time,ircam
Classifier: Development Status :: 3 - Alpha
Classifier: Intended Audience :: Developers
Classifier: Intended Audience :: Science/Research
Classifier: Topic :: Multimedia :: Sound/Audio
Classifier: Topic :: Software Development :: Libraries :: Python Modules
Classifier: License :: OSI Approved :: MIT License
Classifier: Programming Language :: Python :: 3
Classifier: Programming Language :: Python :: 3.8
Classifier: Programming Language :: Python :: 3.9
Classifier: Programming Language :: Python :: 3.10
Classifier: Programming Language :: Python :: 3.11
Classifier: Programming Language :: Python :: 3.12
Requires-Python: >=3.8
License-File: LICENSE
Requires-Dist: python-osc>=1.8.0
Provides-Extra: dev
Requires-Dist: pytest>=7.0.0; extra == "dev"
Requires-Dist: pytest-cov>=4.0.0; extra == "dev"
Requires-Dist: black>=23.0.0; extra == "dev"
Requires-Dist: isort>=5.12.0; extra == "dev"
Requires-Dist: mypy>=1.0.0; extra == "dev"
Dynamic: license-file
